embox/__init__.py
embox/__version__.py
embox/FDTD/__init__.py
embox/FDTD/grid.py
embox/electrostatic/__init__.py
embox/electrostatic/__log__.py
embox/electrostatic/basecharge.py
embox/electrostatic/charge.py
embox/electrostatic/linecharge.py
embox/electrostatic/pointcharge.py
embox/geomesh/__init__.py
embox/geomesh/line.py
embox/geomesh/point.py
embox/geomesh/vector.py
embox/math/__init__.py
embox/math/coordinates.py
embox/math/vector.py
embox/postprocessor/__config__.py
embox/postprocessor/__init__.py
embox/postprocessor/_config.py
embox/postprocessor/plot.py
embox/postprocessor/tools.py
empy/__init__.py
empy/__version__.py
empy/coordinates.py
empy/plot.py
empy/vector.py
empy/FDTD/__init__.py
empy/FDTD/grid.py
empy/electrostatic/__init__.py
empy/electrostatic/__log__.py
empy/electrostatic/charge.py
empy/math/__init__.py
empy/math/coordinates.py
empy/math/vector.py
empy/plot/__init__.py
empy/plot/plot.py
empy/postprocess/__init__.py
empy/postprocess/plot.py
empy/postprocess/tools.py
empy/postprocessor/__init__.py
empy/postprocessor/plot.py
empy/postprocessor/tools.py
embox-0.0.11.dist-info/LICENSE
embox-0.0.11.dist-info/METADATA
embox-0.0.11.dist-info/WHEEL
embox-0.0.11.dist-info/top_level.txt
embox-0.0.11.dist-info/RECORD
