Metadata-Version: 2.1
Name: embox
Version: 0.0.11
Summary: Fundamentals of Electromagnetic with Python
Home-page: https://github.com/WilliamCodeBox/embox
Author: WilliamCodeBox
Author-email: codequote@163.com
License: GNU General Public License v3 (GPLv3)
Platform: UNKNOWN
Classifier: Development Status :: 2 - Pre-Alpha
Classifier: Intended Audience :: Education
Classifier: Intended Audience :: Science/Research
Classifier: Natural Language :: English
Classifier: Natural Language :: Chinese (Simplified)
Classifier: Operating System :: MacOS
Classifier: Topic :: Education
Classifier: Topic :: Scientific/Engineering :: Physics
Classifier: License :: OSI Approved :: GNU General Public License v3 (GPLv3)
Classifier: Programming Language :: Python
Classifier: Programming Language :: Python :: 3
Classifier: Programming Language :: Python :: 3.6
Classifier: Programming Language :: Python :: Implementation :: CPython
Classifier: Programming Language :: Python :: Implementation :: PyPy
Requires-Python: >=3.6.0
Requires-Dist: numpy (>=1.19.2)
Requires-Dist: scipy (>=1.5.2)
Requires-Dist: mpi4py (>=3.0.3)
Provides-Extra: postprocessor
Requires-Dist: matplotlib (>=3.3.2) ; extra == 'postprocessor'
Provides-Extra: test
Requires-Dist: coverage (>=5.3.0) ; extra == 'test'
